{
	"info": {
		"script": {
			"0": {
				"script": "guild_move"
			}
		}
	},
	"stand": {
		"0": {
			"origin": {
				"x": 25,
				"y": 74
			},
			"delay": 1000,
			"": "/Npc/2010011/stand/0",
			"__w": 50,
			"__h": 74
		},
		"1": {
			"origin": {
				"x": 25,
				"y": 74
			},
			"delay": 100,
			"": "/Npc/2010011/stand/1",
			"__w": 50,
			"__h": 74
		},
		"2": {
			"origin": {
				"x": 25,
				"y": 74
			},
			"delay": 100,
			"": "/Npc/2010011/stand/2",
			"__w": 50,
			"__h": 74
		},
		"3": {
			"origin": {
				"x": 25,
				"y": 74
			},
			"delay": 100,
			"": "/Npc/2010011/stand/0",
			"__w": 50,
			"__h": 74
		},
		"4": {
			"origin": {
				"x": 25,
				"y": 74
			},
			"delay": 100,
			"": "/Npc/2010011/stand/1",
			"__w": 50,
			"__h": 74
		},
		"5": {
			"origin": {
				"x": 25,
				"y": 74
			},
			"delay": 100,
			"": "/Npc/2010011/stand/2",
			"__w": 50,
			"__h": 74
		},
		"6": {
			"origin": {
				"x": 25,
				"y": 74
			},
			"delay": 1000,
			"": "/Npc/2010011/stand/0",
			"__w": 50,
			"__h": 74
		},
		"7": {
			"origin": {
				"x": 25,
				"y": 74
			},
			"delay": 100,
			"": "/Npc/2010011/stand/1",
			"__w": 50,
			"__h": 74
		},
		"8": {
			"origin": {
				"x": 25,
				"y": 74
			},
			"delay": 100,
			"": "/Npc/2010011/stand/2",
			"__w": 50,
			"__h": 74
		},
		"9": {
			"origin": {
				"x": 25,
				"y": 74
			},
			"delay": 100,
			"": "/Npc/2010011/stand/0",
			"__w": 50,
			"__h": 74
		},
		"10": {
			"origin": {
				"x": 25,
				"y": 74
			},
			"delay": 100,
			"": "/Npc/2010011/stand/1",
			"__w": 50,
			"__h": 74
		},
		"11": {
			"origin": {
				"x": 25,
				"y": 74
			},
			"delay": 100,
			"": "/Npc/2010011/stand/2",
			"__w": 50,
			"__h": 74
		},
		"12": {
			"origin": {
				"x": 25,
				"y": 74
			},
			"delay": 600,
			"": "/Npc/2010011/stand/0",
			"__w": 50,
			"__h": 74
		},
		"13": {
			"origin": {
				"x": 25,
				"y": 74
			},
			"delay": 100,
			"": "/Npc/2010011/stand/1",
			"__w": 50,
			"__h": 74
		},
		"14": {
			"origin": {
				"x": 25,
				"y": 74
			},
			"delay": 100,
			"": "/Npc/2010011/stand/2",
			"__w": 50,
			"__h": 74
		}
	},
	"say": {
		"0": {
			"origin": {
				"x": 25,
				"y": 74
			},
			"delay": 1000,
			"": "/Npc/2010011/stand/0",
			"__w": 50,
			"__h": 74
		},
		"1": {
			"origin": {
				"x": 25,
				"y": 74
			},
			"delay": 200,
			"": "/Npc/2010011/say/1",
			"__w": 50,
			"__h": 74
		},
		"2": {
			"origin": {
				"x": 25,
				"y": 74
			},
			"delay": 100,
			"": "/Npc/2010011/stand/0",
			"__w": 50,
			"__h": 74
		},
		"3": {
			"origin": {
				"x": 25,
				"y": 74
			},
			"delay": 100,
			"": "/Npc/2010011/say/1",
			"__w": 50,
			"__h": 74
		},
		"4": {
			"origin": {
				"x": 25,
				"y": 74
			},
			"delay": 100,
			"": "/Npc/2010011/stand/0",
			"__w": 50,
			"__h": 74
		},
		"5": {
			"origin": {
				"x": 25,
				"y": 74
			},
			"delay": 200,
			"": "/Npc/2010011/say/1",
			"__w": 50,
			"__h": 74
		},
		"6": {
			"origin": {
				"x": 25,
				"y": 74
			},
			"delay": 600,
			"": "/Npc/2010011/stand/0",
			"__w": 50,
			"__h": 74
		},
		"7": {
			"origin": {
				"x": 25,
				"y": 74
			},
			"delay": 100,
			"": "/Npc/2010011/say/1",
			"__w": 50,
			"__h": 74
		},
		"8": {
			"origin": {
				"x": 25,
				"y": 74
			},
			"delay": 200,
			"": "/Npc/2010011/stand/0",
			"__w": 50,
			"__h": 74
		},
		"9": {
			"origin": {
				"x": 25,
				"y": 74
			},
			"delay": 100,
			"": "/Npc/2010011/say/1",
			"__w": 50,
			"__h": 74
		},
		"10": {
			"origin": {
				"x": 25,
				"y": 74
			},
			"delay": 600,
			"": "/Npc/2010011/stand/0",
			"__w": 50,
			"__h": 74
		},
		"11": {
			"origin": {
				"x": 25,
				"y": 74
			},
			"delay": 200,
			"": "/Npc/2010011/say/1",
			"__w": 50,
			"__h": 74
		},
		"12": {
			"origin": {
				"x": 25,
				"y": 74
			},
			"delay": 600,
			"": "/Npc/2010011/stand/0",
			"__w": 50,
			"__h": 74
		},
		"speak": {
			"0": "s0",
			"1": "s1"
		}
	}
}